pytank/__init__.py
pytank/analysis.py
pytank/aquifer_model.py
pytank/constants/__init__.py
pytank/constants/constants.py
pytank/fluid_model.py
pytank/functions/__init__.py
pytank/functions/helpers.py
pytank/functions/material_balance.py
pytank/functions/optional_functions.py
pytank/functions/pvt_correlations.py
pytank/functions/pvt_interp.py
pytank/functions/pvt_table.py
pytank/functions/utilities.py
pytank/tank.py
pytank/vector_data.py
pytank/well.py
pytank-0.1.5.dist-info/LICENSE
pytank-0.1.5.dist-info/METADATA
pytank-0.1.5.dist-info/WHEEL
pytank-0.1.5.dist-info/RECORD
