Metadata-Version: 2.1
Name: Pytank
Version: 0.1.5
Summary: Library to calculate POES by material balance equations of sub-saturaded Reservories
Author: Erick Michael Villarroel Tenelema
Author-email: erickv2499@gmail.com
Requires-Python: >=3.10,<4.0
Classifier: Programming Language :: Python :: 3
Classifier: Programming Language :: Python :: 3.10
Classifier: Programming Language :: Python :: 3.11
Classifier: Programming Language :: Python :: 3.12
Requires-Dist: matplotlib (>=3.8.2,<4.0.0)
Requires-Dist: numpy (>=1.26.3,<2.0.0)
Requires-Dist: pandas (>=2.1.4,<3.0.0)
Requires-Dist: pandera (>=0.18.3,<0.19.0)
Requires-Dist: scipy (>=1.11.4,<2.0.0)
